<?xml version="1.0" encoding="utf-8"?>
<edmx:Edmx Version="4.0" xmlns:edmx="http://docs.oasis-open.org/odata/ns/edmx">
    <edmx:Reference Uri="../../catalogservice;v=2/Vocabularies(TechnicalName='%2FIWBEP%2FVOC_COMMON',Version='0001',SAP__Origin='')/$value">
        <edmx:Include Namespace="com.sap.vocabularies.Common.v1" Alias="Common"/>
    </edmx:Reference>
    <edmx:Reference Uri="../../catalogservice;v=2/Vocabularies(TechnicalName='%2FIWBEP%2FVOC_UI',Version='0001',SAP__Origin='')/$value">
        <edmx:Include Namespace="com.sap.vocabularies.UI.v1" Alias="UI"/>
    </edmx:Reference>
    <edmx:Reference Uri="../../catalogservice;v=2/Vocabularies(TechnicalName='%2FIWBEP%2FVOC_COMMUNICATION',Version='0001',SAP__Origin='')/$value">
        <edmx:Include Namespace="com.sap.vocabularies.Communication.v1" Alias="Communication"/>
    </edmx:Reference>
    <edmx:Reference Uri="../../catalogservice;v=2/Vocabularies(TechnicalName='%2FIWBEP%2FVOC_PERSONALDATA',Version='0001',SAP__Origin='')/$value">
        <edmx:Include Namespace="com.sap.vocabularies.PersonalData.v1" Alias="PersonalData"/>
    </edmx:Reference>
    <edmx:Reference Uri="../../catalogservice;v=2/Vocabularies(TechnicalName='%2FIWBEP%2FVOC_VALIDATION',Version='0001',SAP__Origin='')/$value">
        <edmx:Include Namespace="Org.OData.Validation.V1" Alias="Validation"/>
    </edmx:Reference>
    <edmx:Reference Uri="../../catalogservice;v=2/Vocabularies(TechnicalName='%2FIWBEP%2FVOC_ANALYTICS',Version='0001',SAP__Origin='')/$value">
        <edmx:Include Namespace="com.sap.vocabularies.Analytics.v1" Alias="Analytics"/>
    </edmx:Reference>
    <edmx:Reference Uri="../../catalogservice;v=2/Vocabularies(TechnicalName='%2FIWBEP%2FVOC_HTML5',Version='0001',SAP__Origin='')/$value">
        <edmx:Include Namespace="com.sap.vocabularies.HTML5.v1" Alias="HTML5"/>
    </edmx:Reference>
    <edmx:Reference Uri="../../../sap/zplist_tp_v2_ui/$metadata">
        <edmx:Include Namespace="ZPLIST_TP_V2_UI" Alias="SAP"/>
    </edmx:Reference>
    <edmx:DataServices>
        <Schema Namespace="zplist_tp_v2_ui_van.v1" xmlns="http://docs.oasis-open.org/odata/ns/edm">
            <Annotations Target="cds_zplist_tp.I_DraftAdministrativeDataType/DraftUUID">
                <Annotation Term="UI.Hidden"/>
            </Annotations>
            <Annotations Target="cds_zplist_tp.I_DraftAdministrativeDataType/DraftEntityType">
                <Annotation Term="UI.Hidden"/>
            </Annotations>
            <Annotations Target="cds_zplist_tp.I_DraftAdministrativeDataType/DraftAccessType">
                <Annotation Term="UI.Hidden"/>
            </Annotations>
            <Annotations Target="cds_zplist_tp.I_DraftAdministrativeDataType/ProcessingStartDateTime">
                <Annotation Term="UI.Hidden"/>
            </Annotations>
            <Annotations Target="cds_zplist_tp.I_DraftAdministrativeDataType/DraftIsKeptByUser">
                <Annotation Term="UI.Hidden"/>
            </Annotations>
            <Annotations Target="cds_zplist_tp.I_DraftAdministrativeDataType/EnqueueStartDateTime">
                <Annotation Term="UI.Hidden"/>
            </Annotations>
            <Annotations Target="cds_zplist_tp.I_DraftAdministrativeDataType/DraftIsCreatedByMe">
                <Annotation Term="UI.Hidden"/>
            </Annotations>
            <Annotations Target="cds_zplist_tp.I_DraftAdministrativeDataType/DraftIsLastChangedByMe">
                <Annotation Term="UI.Hidden"/>
            </Annotations>
            <Annotations Target="cds_zplist_tp.I_DraftAdministrativeDataType/DraftIsProcessedByMe">
                <Annotation Term="UI.Hidden"/>
            </Annotations>
            <Annotations Target="cds_zplist_tp.I_DraftAdministrativeDataType/CreatedByUserDescription">
                <Annotation Term="UI.Hidden"/>
            </Annotations>
            <Annotations Target="cds_zplist_tp.I_DraftAdministrativeDataType/LastChangedByUserDescription">
                <Annotation Term="UI.Hidden"/>
            </Annotations>
            <Annotations Target="cds_zplist_tp.I_DraftAdministrativeDataType/InProcessByUserDescription">
                <Annotation Term="UI.Hidden"/>
            </Annotations>
            <Annotations Target="cds_zplist_tp.AttachmentType/HasDraftEntity">
                <Annotation Term="UI.HiddenFilter"/>
                <Annotation Term="UI.Hidden"/>
            </Annotations>
            <Annotations Target="cds_zplist_tp.AttachmentType/DraftEntityCreationDateTime">
                <Annotation Term="UI.HiddenFilter"/>
                <Annotation Term="UI.Hidden"/>
            </Annotations>
            <Annotations Target="cds_zplist_tp.AttachmentType/DraftEntityLastChangeDateTime">
                <Annotation Term="UI.HiddenFilter"/>
                <Annotation Term="UI.Hidden"/>
            </Annotations>
            <Annotations Target="cds_zplist_tp.AttachmentType/HasActiveEntity">
                <Annotation Term="UI.HiddenFilter"/>
                <Annotation Term="UI.Hidden"/>
            </Annotations>
            <Annotations Target="cds_zplist_tp.AttachmentType/IsActiveEntity">
                <Annotation Term="UI.HiddenFilter"/>
                <Annotation Term="UI.Hidden"/>
            </Annotations>
            <Annotations Target="cds_zplist_tp.AttachmentType/Mimetype">
                <Annotation Term="UI.Hidden"/>
            </Annotations>
            <Annotations Target="cds_zplist_tp.AttachmentType/Filename">
                <Annotation Term="UI.Hidden"/>
            </Annotations>
            <Annotations Target="cds_zplist_tp.AttachmentType/LastChangedAt">
                <Annotation Term="UI.Hidden"/>
            </Annotations>
            <Annotations Target="cds_zplist_tp.AttachmentType/Delete_mc">
                <Annotation Term="UI.Hidden"/>
            </Annotations>
            <Annotations Target="cds_zplist_tp.AttachmentType/Update_mc">
                <Annotation Term="UI.Hidden"/>
            </Annotations>
            <Annotations Target="cds_zplist_tp.AttachmentType">
                <Annotation Term="UI.Facets">
                    <Collection>
                        <Record Type="UI.CollectionFacet">
                            <PropertyValue Property="Label" String="General Information"/>
                            <PropertyValue Property="ID" String="GeneralInfo"/>
                            <PropertyValue Property="Facets">
                                <Collection>
                                    <Record Type="UI.ReferenceFacet">
                                        <PropertyValue Property="Label" String="Upload Attachment"/>
                                        <PropertyValue Property="ID" String="Upload"/>
                                        <PropertyValue Property="Target" AnnotationPath="@UI.FieldGroup#Upload"/>
                                    </Record>
                                </Collection>
                            </PropertyValue>
                        </Record>
                    </Collection>
                </Annotation>
                <Annotation Term="UI.FieldGroup" Qualifier="Upload">
                    <Record>
                        <PropertyValue Property="Data">
                            <Collection>
                                <Record Type="UI.DataField">
                                    <PropertyValue Property="Label" String="Plist"/>
                                    <PropertyValue Property="Value" Path="Plist"/>
                                </Record>
                                <Record Type="UI.DataField">
                                    <PropertyValue Property="Label" String="Attach No"/>
                                    <PropertyValue Property="Value" Path="AttachNo"/>
                                </Record>
                                <Record Type="UI.DataField">
                                    <PropertyValue Property="Label" String="File"/>
                                    <PropertyValue Property="Value" Path="Attachment"/>
                                </Record>
                            </Collection>
                        </PropertyValue>
                    </Record>
                </Annotation>
                <Annotation Term="UI.HeaderInfo">
                    <Record>
                        <PropertyValue Property="TypeName" String="Attachment"/>
                        <PropertyValue Property="TypeNamePlural" String="Attachments"/>
                        <PropertyValue Property="Title">
                            <Record Type="UI.DataField">
                                <PropertyValue Property="Value" Path="Plist"/>
                            </Record>
                        </PropertyValue>
                        <PropertyValue Property="Description">
                            <Record Type="UI.DataField">
                                <PropertyValue Property="Value" Path="Plist"/>
                            </Record>
                        </PropertyValue>
                    </Record>
                </Annotation>
                <Annotation Term="UI.LineItem">
                    <Collection>
                        <Record Type="UI.DataField">
                            <PropertyValue Property="Label" String="Procurement List"/>
                            <PropertyValue Property="Value" Path="Plist"/>
                        </Record>
                        <Record Type="UI.DataField">
                            <PropertyValue Property="Label" String="Attachment No"/>
                            <PropertyValue Property="Value" Path="AttachNo"/>
                        </Record>
                        <Record Type="UI.DataField">
                            <PropertyValue Property="Label" String="File"/>
                            <PropertyValue Property="Value" Path="Attachment"/>
                        </Record>
                    </Collection>
                </Annotation>
            </Annotations>
            <Annotations Target="cds_zplist_tp.ProcurementListType/HasDraftEntity">
                <Annotation Term="UI.HiddenFilter"/>
                <Annotation Term="UI.Hidden"/>
            </Annotations>
            <Annotations Target="cds_zplist_tp.ProcurementListType/DraftEntityCreationDateTime">
                <Annotation Term="UI.HiddenFilter"/>
                <Annotation Term="UI.Hidden"/>
            </Annotations>
            <Annotations Target="cds_zplist_tp.ProcurementListType/DraftEntityLastChangeDateTime">
                <Annotation Term="UI.HiddenFilter"/>
                <Annotation Term="UI.Hidden"/>
            </Annotations>
            <Annotations Target="cds_zplist_tp.ProcurementListType/HasActiveEntity">
                <Annotation Term="UI.HiddenFilter"/>
                <Annotation Term="UI.Hidden"/>
            </Annotations>
            <Annotations Target="cds_zplist_tp.ProcurementListType/IsActiveEntity">
                <Annotation Term="UI.HiddenFilter"/>
                <Annotation Term="UI.Hidden"/>
            </Annotations>
            <Annotations Target="cds_zplist_tp.ProcurementListType/ChangedBy">
                <Annotation Term="UI.Hidden"/>
            </Annotations>
            <Annotations Target="cds_zplist_tp.ProcurementListType/ChangedAt">
                <Annotation Term="UI.Hidden"/>
            </Annotations>
            <Annotations Target="cds_zplist_tp.ProcurementListType/Edit_ac">
                <Annotation Term="UI.Hidden"/>
            </Annotations>
            <Annotations Target="cds_zplist_tp.ProcurementListType/SetStatusComplete_ac">
                <Annotation Term="UI.Hidden"/>
            </Annotations>
            <Annotations Target="cds_zplist_tp.ProcurementListType/Delete_mc">
                <Annotation Term="UI.Hidden"/>
            </Annotations>
            <Annotations Target="cds_zplist_tp.ProcurementListType/Update_mc">
                <Annotation Term="UI.Hidden"/>
            </Annotations>
            <Annotations Target="cds_zplist_tp.ProcurementListType/to_PLAttach_oc">
                <Annotation Term="UI.Hidden"/>
            </Annotations>
            <Annotations Target="cds_zplist_tp.ProcurementListType">
                <Annotation Term="UI.DataPoint" Qualifier="Status">
                    <Record>
                        <PropertyValue Property="Value" Path="Status"/>
                        <PropertyValue Property="Title" String="Status"/>
                    </Record>
                </Annotation>
                <Annotation Term="UI.Facets">
                    <Collection>
                        <Record Type="UI.CollectionFacet">
                            <PropertyValue Property="Label" String="Procuremen List - Plate Number"/>
                            <PropertyValue Property="ID" String="General"/>
                            <PropertyValue Property="Facets">
                                <Collection>
                                    <Record Type="UI.ReferenceFacet">
                                        <PropertyValue Property="Label" String="Plate# to be replaced"/>
                                        <PropertyValue Property="ID" String="Plate"/>
                                        <PropertyValue Property="Target" AnnotationPath="@UI.FieldGroup#Plate"/>
                                    </Record>
                                </Collection>
                            </PropertyValue>
                        </Record>
                        <Record Type="UI.ReferenceFacet">
                            <PropertyValue Property="Label" String="Additional Indormation"/>
                            <PropertyValue Property="ID" String="AdditionalInfo"/>
                            <PropertyValue Property="Target" AnnotationPath="@UI.FieldGroup#AdditionalInfo"/>
                        </Record>
                        <Record Type="UI.ReferenceFacet">
                            <PropertyValue Property="Label" String="Upload Attachments"/>
                            <PropertyValue Property="ID" String="Upload"/>
                            <PropertyValue Property="Target" AnnotationPath="to_PLAttach/@UI.LineItem"/>
                        </Record>
                    </Collection>
                </Annotation>
                <Annotation Term="UI.HeaderFacets">
                    <Collection>
                        <Record Type="UI.ReferenceFacet">
                            <PropertyValue Property="ID" String="HeaderStatus"/>
                            <PropertyValue Property="Target" AnnotationPath="@UI.DataPoint#Status"/>
                        </Record>
                    </Collection>
                </Annotation>
                <Annotation Term="UI.FieldGroup" Qualifier="AdditionalInfo">
                    <Record>
                        <PropertyValue Property="Data">
                            <Collection>
                                <Record Type="UI.DataField">
                                    <PropertyValue Property="Label" String="Diso"/>
                                    <PropertyValue Property="Value" Path="Diso"/>
                                </Record>
                                <Record Type="UI.DataField">
                                    <PropertyValue Property="Label" String="Diso Options"/>
                                    <PropertyValue Property="Value" Path="DisoOptions"/>
                                </Record>
                                <Record Type="UI.DataField">
                                    <PropertyValue Property="Label" String="Comments"/>
                                    <PropertyValue Property="Value" Path="Comments"/>
                                </Record>
                            </Collection>
                        </PropertyValue>
                    </Record>
                </Annotation>
                <Annotation Term="UI.FieldGroup" Qualifier="Plate">
                    <Record>
                        <PropertyValue Property="Data">
                            <Collection>
                                <Record Type="UI.DataField">
                                    <PropertyValue Property="Label" String="Plate#"/>
                                    <PropertyValue Property="Value" Path="PlateNo"/>
                                </Record>
                            </Collection>
                        </PropertyValue>
                    </Record>
                </Annotation>
                <Annotation Term="UI.HeaderInfo">
                    <Record>
                        <PropertyValue Property="TypeName" String="Procurement List"/>
                        <PropertyValue Property="TypeNamePlural" String="Procurement Lists"/>
                        <PropertyValue Property="Title">
                            <Record Type="UI.DataField">
                                <PropertyValue Property="Label" String="Procurement List"/>
                                <PropertyValue Property="Value" Path="Plist"/>
                            </Record>
                        </PropertyValue>
                        <PropertyValue Property="Description">
                            <Record Type="UI.DataField">
                                <PropertyValue Property="Label" String="Manage Procurement List"/>
                                <PropertyValue Property="Value" Path="Zzuser"/>
                            </Record>
                        </PropertyValue>
                    </Record>
                </Annotation>
                <Annotation Term="UI.Identification">
                    <Collection>
                        <Record Type="UI.DataFieldForAction">
                            <PropertyValue Property="Label" String="Update Status"/>
                            <PropertyValue Property="Action" String="cds_zplist_tp.cds_zplist_tp_Entities/SetStatusComplete"/>
                            <PropertyValue Property="InvocationGrouping" EnumMember="UI.OperationGroupingType/Isolated"/>
                            <Annotation Term="UI.Importance" EnumMember="UI.ImportanceType/High"/>
                        </Record>
                    </Collection>
                </Annotation>
                <Annotation Term="UI.LineItem">
                    <Collection>
                        <Record Type="UI.DataField">
                            <PropertyValue Property="Label" String="Procurement List"/>
                            <PropertyValue Property="Value" Path="Plist"/>
                        </Record>
                        <Record Type="UI.DataFieldForAction">
                            <PropertyValue Property="Label" String="Update Status"/>
                            <PropertyValue Property="Action" String="cds_zplist_tp.cds_zplist_tp_Entities/SetStatusComplete"/>
                            <PropertyValue Property="InvocationGrouping" EnumMember="UI.OperationGroupingType/Isolated"/>
                            <Annotation Term="UI.Importance" EnumMember="UI.ImportanceType/High"/>
                        </Record>
                        <Record Type="UI.DataField">
                            <PropertyValue Property="Label" String="Name"/>
                            <PropertyValue Property="Value" Path="Name"/>
                        </Record>
                        <Record Type="UI.DataField">
                            <PropertyValue Property="Label" String="Plate#"/>
                            <PropertyValue Property="Value" Path="PlateNo"/>
                        </Record>
                        <Record Type="UI.DataField">
                            <PropertyValue Property="Label" String="Change Request#"/>
                            <PropertyValue Property="Value" Path="EstChgReq"/>
                        </Record>
                        <Record Type="UI.DataField">
                            <PropertyValue Property="Label" String="Quantity"/>
                            <PropertyValue Property="Value" Path="Qty"/>
                        </Record>
                        <Record Type="UI.DataField">
                            <PropertyValue Property="Label" String="Unit"/>
                            <PropertyValue Property="Value" Path="Unit"/>
                        </Record>
                        <Record Type="UI.DataField">
                            <PropertyValue Property="Label" String="Division"/>
                            <PropertyValue Property="Value" Path="Division"/>
                        </Record>
                        <Record Type="UI.DataField">
                            <PropertyValue Property="Label" String="Owner"/>
                            <PropertyValue Property="Value" Path="Owner"/>
                        </Record>
                        <Record Type="UI.DataField">
                            <PropertyValue Property="Label" String="User"/>
                            <PropertyValue Property="Value" Path="Zzuser"/>
                        </Record>
                        <Record Type="UI.DataField">
                            <PropertyValue Property="Label" String="Diso"/>
                            <PropertyValue Property="Value" Path="Diso"/>
                        </Record>
                        <Record Type="UI.DataField">
                            <PropertyValue Property="Label" String="Diso Options"/>
                            <PropertyValue Property="Value" Path="DisoOptions"/>
                        </Record>
                        <Record Type="UI.DataField">
                            <PropertyValue Property="Label" String="Status"/>
                            <PropertyValue Property="Value" Path="Status"/>
                        </Record>
                        <Record Type="UI.DataField">
                            <PropertyValue Property="Label" String="Approved By"/>
                            <PropertyValue Property="Value" Path="ApprovedBy"/>
                        </Record>
                    </Collection>
                </Annotation>
                <Annotation Term="UI.SelectionFields">
                    <Collection>
                        <PropertyPath>Plist</PropertyPath>
                        <PropertyPath>CreatedAt</PropertyPath>
                        <PropertyPath>CreatedBy</PropertyPath>
                        <PropertyPath>PlateNo</PropertyPath>
                        <PropertyPath>EstChgReq</PropertyPath>
                        <PropertyPath>Division</PropertyPath>
                        <PropertyPath>Owner</PropertyPath>
                        <PropertyPath>Zzuser</PropertyPath>
                        <PropertyPath>Status</PropertyPath>
                    </Collection>
                </Annotation>
            </Annotations>
        </Schema>
    </edmx:DataServices>
</edmx:Edmx>